{"N\u00ba da ARP (a)":{"0":"037-2011","1":"052-2011","2":"035-2011","3":"053-2011","4":"033-2011","5":"038-2011","6":"076-2011","7":"021-2012","8":"058-2011","9":"080-2011","10":"013-2012","11":"063-2012","12":"013-2012","13":"013-2012","14":"036-2012","15":"049-2012","16":"047-2013","17":"033-2013","18":"012-2014","19":"044-2014","20":"050-2014","21":"017-2014","22":0,"23":0,"24":0,"25":0,"26":0,"27":"003-2015","28":0,"29":"024-2015","30":"016-2015","31":"042-2015","32":"014-2015","33":"026-2015","34":0,"35":0,"36":"022-2015","37":0,"38":"037-2016","39":"043-2015","40":0,"41":"048-2016","42":"037-2016","43":"010-2016","44":0,"45":"049-2015","46":0,"47":"086-2016","48":"016-2017","49":"004-2017","50":"005-2017","51":"013-2017","52":0,"53":0,"54":0,"55":"034-2017","56":"035-2017","57":"036-2017","58":"037-2017","59":"006-2017","60":"007-2017","61":"008-2017","62":"009-2017","63":"010-2017","64":"011-2017","65":"012-2017","66":"060-2017","67":"068-2017","68":"016-2017","69":0,"70":"021-2017","71":"043-2017","72":"048-2017","73":"019-2017","74":"051-2017","75":0,"76":0,"77":0,"78":0,"79":"038-2017","80":0,"81":0,"82":"092-2017","83":"015-2018","84":"035-2018","85":"036-2018","86":"036-2018","87":"040-2018","88":"045-2018","89":"035-2018","90":0,"91":"059-2018","92":0,"93":"006-2018","94":"004-2018","95":"073-2018","96":"045\/2018","97":"069\/2018","98":"072\/2018","99":0,"100":0,"101":0,"102":"073-2018","103":"045-2019","104":0,"105":"062-2019","106":0,"107":0,"108":0,"109":0,"110":"040-2019","111":0,"112":0,"113":0,"114":0},"N\u00ba do Aditivo (b)":{"0":1,"1":1,"2":1,"3":1,"4":1,"5":1,"6":1,"7":1,"8":1,"9":1,"10":1,"11":1,"12":3,"13":2,"14":1,"15":1,"16":1,"17":1,"18":1,"19":1,"20":1,"21":1,"22":0,"23":0,"24":0,"25":0,"26":0,"27":1,"28":0,"29":1,"30":1,"31":1,"32":1,"33":1,"34":0,"35":0,"36":1,"37":0,"38":1,"39":1,"40":0,"41":1,"42":2,"43":1,"44":0,"45":1,"46":0,"47":1,"48":1,"49":1,"50":1,"51":1,"52":0,"53":0,"54":0,"55":1,"56":1,"57":1,"58":1,"59":1,"60":1,"61":1,"62":1,"63":1,"64":1,"65":1,"66":1,"67":1,"68":2,"69":0,"70":1,"71":1,"72":1,"73":1,"74":1,"75":0,"76":0,"77":0,"78":0,"79":1,"80":0,"81":0,"82":1,"83":1,"84":1,"85":1,"86":2,"87":1,"88":1,"89":2,"90":0,"91":1,"92":0,"93":1,"94":1,"95":1,"96":2,"97":1,"98":1,"99":0,"100":0,"101":0,"102":2,"103":1,"104":0,"105":1,"106":0,"107":0,"108":0,"109":0,"110":1,"111":0,"112":0,"113":0,"114":0},"Objeto (c)":{"0":"Acr\u00e9scimo de quantidades e, consequente acrescimo de valor","1":"Acr\u00e9scimos de quantidades e, consequente acr\u00e9scimo de valor","2":"Acr\u00e9scimos de quantidades e, consequente acr\u00e9scimo de valor","3":"Acr\u00e9scimos de quantidades e, consequente acr\u00e9scimo de valor","4":"Registro de Pre\u00e7os para Aquisi\u00e7\u00e3o Eventual de Material de Expediente.","5":"Acr\u00e9scimo de 25%","6":"Acr\u00e9scimo de valor ao contrato original","7":"Altera\u00e7\u00e3o da raz\u00e3o social na Ata de Registro de Pre\u00e7os n\u00ba. 021\/2012.","8":"Reequil\u00edbrio Econ\u00f4mico-Financeiro do item 01.","9":"Altera\u00e7\u00e3o de Marca dos itens 01, 02 e 03 da subcl\u00e1usula 2.1","10":"Altera\u00e7\u00e3o de Marca e especifica\u00e7\u00f5es dos itens 02, 04 e 06 constantes da subcl\u00e1usula 2.1.","11":"Altera\u00e7\u00e3o da especifica\u00e7\u00e3o do item 31 do lote II.","12":"Acr\u00e9scimo de 25% (vinte e cinco) as quantidades contratadas conforme subcl\u00e1usula 2.1. Valor do Aditamento: R$ 39.407,09 (Trinta e nove mil, quatrocentos e sete reais e nove centavos).","13":"Altera\u00e7\u00e3o de Marca dos itens 1, 2 e 5 bem como valor dos itens 1, 2, 3, 4 e 5 constantes da subcl\u00e1usula 2.1.","14":"Reajuste de pre\u00e7o","15":"Reajuste de valor em fun\u00e7\u00e3o do Reequil\u00edbrio Econ\u00f4mico-Financeiro.","16":"Retifica\u00e7\u00e3o da Cl\u00e1usula Segunda da Ata de Registro de Pre\u00e7os.","17":"Equil\u00edbrio econ\u00f4mico-financeiro do item 23 do grupo 06 que era de R$ 2,90 (dois reais e noventa centavos) passa a ser de R$ 4,23 (quatro reais e vinte e tr\u00eas centavos).","18":"Altera\u00e7\u00e3o da especifica\u00e7\u00e3o do item 328 do lote XVIII da Ata de Registro de Pre\u00e7os. Dividiu o item em 10 unidade da marca SAMSUNG e 20 da marca Elgin. O valor e a quantidade total permaneceram o mesmo.","19":"Altera\u00e7\u00e3o da especifica\u00e7\u00e3o de produto referente ao modelo do item 6, constante da subcl\u00e1usula 2.1 da Ata de Registro de Pre\u00e7os\r Valor do Aditamento: -","20":"Altera\u00e7\u00e3o da especifica\u00e7\u00e3o de produto, referente \u00e0 marca e ao modelo do Item 7, constante na subcl\u00e1usula 2.1, para:\r Televisor LED de 60\", marca\/modelo: SAMSUNG\/SMART TV UN60H6300","21":"Retifica\u00e7\u00e3o do valor contido no campo\/coluna \"Pre\u00e7o Unit\u00e1rio\" do item 09, Lote II, p\/ R$ 1.225,00.\r\n\"Licen\u00e7a de uso ad perpetuam de softwares de gerenciamento dos coletores e catracas. As Licen\u00e7as de Uso dever\u00e3o possuir a capacidade de interoperabilidade com sistema \u201cRonda Acesso\u201d. A exig\u00eancia de compatibilidade com o software \u2013 Ronda Acesso (SeniorSistemas), deve-se ao fato da atual exist\u00eancia do referido Programa no controle de Acesso do Minist\u00e9rio P\u00fablico do Estado do Par\u00e1, com 12 meses de atualiza\u00e7\u00e3o.\"","22":"N\u00c3O H\u00c1 PUBLICA\u00c7\u00c3O NESTE PER\u00cdODO","23":"N\u00c3O H\u00c1 PUBLICA\u00c7\u00c3O NESTE PER\u00cdODO","24":"N\u00c3O H\u00c1 PUBLICA\u00c7\u00c3O NESTE PER\u00cdODO","25":"N\u00c3O H\u00c1 PUBLICA\u00c7\u00c3O NESTE PER\u00cdODO","26":"N\u00c3O H\u00c1 PUBLICA\u00c7\u00c3O NESTE PER\u00cdODO","27":"altera\u00e7\u00e3o da marca e modelo de produto referente ao modelo do item 01, constante da subcl\u00e1usula 2.1 da Ata de Registro de Pre\u00e7os","28":"N\u00c3O H\u00c1 PUBLICA\u00c7\u00c3O NESTE PER\u00cdODO","29":"Redu\u00e7\u00e3o do pre\u00e7o unit\u00e1rio e pre\u00e7o total estimado do item 23, nos termos da renegocia\u00e7\u00e3o de pre\u00e7os junto \u00e0 fornecedora, passando para os seguintes valores: valor unit\u00e1rio R$ 118,00; valor total do item R$ 2.596,00; valor global estimado da Ata R$ 7.840,80.","30":"Altera\u00e7\u00e3o da Cl\u00e1usula 2\u00aa do Contrato original que trata de pre\u00e7o, em fun\u00e7\u00e3o do reequil\u00edbrio econ\u00f4mico (reajuste de 9,43%).","31":"Ficam retificados os valores dos pre\u00e7os unit\u00e1rios dos seguintes itens para:\r item 68 - R$ 510,00\r; item 69 -; R$ 320,00\r; item 70 - R$ 330,00\r; item 71 - R$ 540,00\r; item 72 - R$ 480,00\r; item 73 - R$ 650,00\r; item 74 - R$ 900,00\r; item 65 - R$ 1.100,00","32":"Altera\u00e7\u00e3o da Cl\u00e1usula 2\u00aa do contrato original que trata de pre\u00e7o, em fun\u00e7\u00e3o do reequil\u00edbrio econ\u00f4mico-financeiro.","33":"Considerando o reequil\u00edbrio econ\u00f4mico comprovado no protocolo n.\u00ba 26416\/2015, os valores unit\u00e1rios dos itens 04 e 05 ser\u00e3o revisados para:\r Item 04 (15 unidades): R$ 6.310,00 (valor unit\u00e1rio reequilibrado); R$ 94.650,00 (valor total estimado reequilibrado).\r Item 05 (10 unidades): R$ 7.990,00 (valor unit\u00e1rio reequilibrado); R$ 79.900,00 (valor total estimado reequilibrado).","34":"N\u00c3O H\u00c1 PUBLICA\u00c7\u00c3O NESTE PER\u00cdODO","35":"N\u00c3O H\u00c1 PUBLICA\u00c7\u00c3O NESTE PER\u00cdODO","36":"Altera\u00e7\u00e3o dos valores unit\u00e1rios dos itens constantes na Cl\u00e1us. 2\u00aa, em fun\u00e7\u00e3o do reequil\u00edbrio econ\u00f4mico-financeiro, conforme protocolo n.\u00ba 53835\/2015.","37":"N\u00c3O H\u00c1 PUBLICA\u00c7\u00c3O NESTE PER\u00cdODO","38":"Corre\u00e7\u00e3o da especifica\u00e7\u00e3o do item 6 da ARP, coadunando com o descritivo do Termo de Refer\u00eancia, para: televisor led de 42\u201d full hd, conversor digital integrado, tela: widescreen (16:9), sinais de pc; alto falantes integrados, m\u00ednimo 01 entrada usb, m\u00ednimo 02 entradas hdmi, sa\u00edda p\/ \u00e1udio, sistema de cor: ntsc\/pal-m, fun\u00e7\u00f5es: mute \/ mts \/ sleep \/ closed caption, controle remoto. Marca de refer\u00eancia: panasonic, samsung, similar ou superior. (cota principal do item 06 - 75% da sua quantidade original \u2013 participa\u00e7\u00e3o aberta). Marca: AOC. Fabricante: AOC (Envision). Modelo\/Vers\u00e3o: LE43D1452.","39":"Altera\u00e7\u00e3o da Cl\u00e1usula 2\u00aa, que trata do pre\u00e7o, em fun\u00e7\u00e3o do reequil\u00edbrio econ\u00f4mico-financeiro, conforme prot. 18485\/2016.","40":"N\u00c3O H\u00c1 PUBLICA\u00c7\u00c3O NESTE PER\u00cdODO","41":"Corre\u00e7\u00e3o dos pre\u00e7os dos itens 106 e 211, dos lotes III e XII - MATERIAL EL\u00c9TRICO","42":"Corre\u00e7\u00e3o da descri\u00e7\u00e3o dos itens 6 e 7 da ARP, coadunando com a proposta da Contratada realizada em 24\/02\/16, embora tenha sido consignado para tais itens produto com especifica\u00e7\u00e3o superior ao solicitado no Termo de Refer\u00eancia, para: TELEVISOR LED de 43\u201d FULL HD, conforme especifica\u00e7\u00f5es t\u00e9cnicas da proposta. Marca: AOC. Fabricante: AOC (Envision). Modelo\/Vers\u00e3o: LE43D1452. Cota Principal do item 06 - 75% da sua quantidade original \u2013 participa\u00e7\u00e3o aberta.","43":"Altera\u00e7\u00e3o da subcl\u00e1usula 2.1 da ARP original, especificamente no item 08 da tabela, quanto ao tamanho do liquidificador, passando de 1,5 para 2,1 litros. N\u00e3o houve altera\u00e7\u00e3o do valor.","44":"N\u00c3O H\u00c1 PUBLICA\u00c7\u00c3O NESTE PER\u00cdODO","45":"Fica alterada a cl\u00e1usula segunda que trata do PRE\u00c7O, em raz\u00e3o do reequil\u00edbrio econ\u00f4mico-financeiro de 19,71%, a contar de 10\/08\/16, passando o valor do item 03 de R$ 136,18\/und para R$ 163,02\/und e o valor total de R$ 27.236,00 para R$ 32.604,00 (diferen\u00e7a de R$ 5.368,00).","46":"N\u00c3O H\u00c1 PUBLICA\u00c7\u00c3O NESTE PER\u00cdODO","47":"retifica\u00e7\u00e3o do valor contido no campo\/coluna \"pre\u00e7o unit\u00e1rio\" do item 55, lote XII","48":"Altera\u00e7\u00e3o da cl\u00e1usula segunda da ARP, considerando equ\u00edvoco no valor mensal do item 9, lote III, passando para R$ 4.805,20.","49":"Repactua\u00e7\u00e3o de valores, em rela\u00e7\u00e3o \u00e0 m\u00e3o de obra, derivada de conven\u00e7\u00e3o coletiva de trabalho 2017\/2018.","50":"Repactua\u00e7\u00e3o de valores, em rela\u00e7\u00e3o \u00e0 m\u00e3o de obra, derivada de conven\u00e7\u00e3o coletiva de trabalho 2017\/2018.","51":"Repactua\u00e7\u00e3o de valores constantes da cl\u00e1usula segunda (DO PRE\u00c7O), especificamente quanto \u00e0 m\u00e3o de obra, derivada da Conven\u00e7\u00e3o Coletiva de Trabalho 2017\/2018.","52":"N\u00c3O H\u00c1 PUBLICA\u00c7\u00c3O NESTE PER\u00cdODO","53":"N\u00c3O H\u00c1 PUBLICA\u00c7\u00c3O NESTE PER\u00cdODO","54":"N\u00c3O H\u00c1 PUBLICA\u00c7\u00c3O NESTE PER\u00cdODO","55":"Reequil\u00edbrio econ\u00f4mico-financeiro dos valores unit\u00e1rios dos itens constantes na Cl\u00e1usula 2\u00aa.","56":"Reequil\u00edbrio econ\u00f4mico-financeiro dos valores unit\u00e1rios dos itens constantes na Cl\u00e1usula 2\u00aa.","57":"Reequil\u00edbrio econ\u00f4mico-financeiro dos valores unit\u00e1rios dos itens constantes na Cl\u00e1usula 2\u00aa.","58":"Reequil\u00edbrio econ\u00f4mico-financeiro dos valores unit\u00e1rios dos itens constantes na Cl\u00e1usula 2\u00aa.","59":"Reequil\u00edbrio econ\u00f4mico-financeiro dos valores unit\u00e1rios dos itens constantes na Cl\u00e1usula 2\u00aa.","60":"Reequil\u00edbrio econ\u00f4mico-financeiro dos valores unit\u00e1rios dos itens constantes na Cl\u00e1usula 2\u00aa.","61":"Reequil\u00edbrio econ\u00f4mico-financeiro dos valores unit\u00e1rios dos itens constantes na Cl\u00e1usula 2\u00aa.","62":"Reequil\u00edbrio econ\u00f4mico-financeiro dos valores unit\u00e1rios dos itens constantes na Cl\u00e1usula 2\u00aa.","63":"Reequil\u00edbrio econ\u00f4mico-financeiro dos valores unit\u00e1rios dos itens constantes na Cl\u00e1usula 2\u00aa.","64":"Reequil\u00edbrio econ\u00f4mico-financeiro dos valores unit\u00e1rios dos itens constantes na Cl\u00e1usula 2\u00aa.","65":"Reequil\u00edbrio econ\u00f4mico-financeiro dos valores unit\u00e1rios dos itens constantes na Cl\u00e1usula 2\u00aa.","66":"Retifica\u00e7\u00e3o do valor unit\u00e1rio do item 22 - Bandeja de fixa\u00e7\u00e3o dupla 19x1U. MARCA: MEKANINA. MODELO: 19X1UX300M. Valor unit\u00e1rio de R$ 123,41 para R$ 77,79.","67":"Retifica\u00e7\u00e3o dos valores contidos nos campos\/colunas \"Pre\u00e7o Unit\u00e1rio\" e \"Valor Total\" dos itens 15 (Lote 7) e 17 (Lote 8), e campo\/coluna \"Valor Total\" do item 21 (Lote 10).\n- Item 15: Pre\u00e7o Unit\u00e1rio = R$ 46,90; Valor Total = R$ 4.690,00;\n- Item 17: Pre\u00e7o Unit\u00e1rio = R$ 48,20; Valor Total = R$ 4.820,00;\n- Item 17: Pre\u00e7o Unit\u00e1rio = R$ 49,19; Valor Total = R$ 4.919,00.","68":"Altera\u00e7\u00e3o da cl\u00e1usula segunda da ARP, que trata do PRE\u00c7O, em raz\u00e3o do reequil\u00edbrio econ\u00f4mico-financeiro, conforme protocolo n\u00ba6465\/2017.","69":"N\u00c3O H\u00c1 PUBLICA\u00c7\u00c3O NESTE PER\u00cdODO","70":"Fica alterada a cl\u00e1usula segunda do contrato original, quanto ao modelo e especifica\u00e7\u00e3o (capacidade) do item 02.","71":"Fica alterada a cl\u00e1usula segunda da ARP, em fun\u00e7\u00e3o do reequil\u00edbrio econ\u00f4mico-financeiro, passando do valor mensal registrado de R$ 6.000,00 para o valor mensal reeequilibrado de R$ 6.391,58.","72":"Fica alterada a cl\u00e1usula primeira da ARP, quanto ao modelo do item 02.","73":"Altera\u00e7\u00e3o de marca e modelo do item 12, devido descontinuidade na fabrica\u00e7\u00e3o, sendo o novo modelo (Marca CONSUL, Modelo CC18DBBNA), de qualidade superior ao equipamento substitu\u00eddo.","74":"Altera\u00e7\u00e3o da cl\u00e1usula primeira do instrumento contratual original, quanto ao modelo, marca e especifica\u00e7\u00e3o dos itens 09 e 10.","75":"N\u00c3O H\u00c1 PUBLICA\u00c7\u00c3O NESTE PER\u00cdODO","76":"N\u00c3O H\u00c1 PUBLICA\u00c7\u00c3O NESTE PER\u00cdODO","77":"N\u00c3O H\u00c1 PUBLICA\u00c7\u00c3O NESTE PER\u00cdODO","78":"N\u00c3O H\u00c1 PUBLICA\u00c7\u00c3O NESTE PER\u00cdODO","79":"Repactua\u00e7\u00e3o dos valores constantes na cl\u00e1usula segunda (DO PRE\u00c7O), especificamente quanto \u00e0 m\u00e3o de obra, passando o valor unit\u00e1rio de R$ 2.755,00 para o repactuado de R$ 2.944,50.\nValor mensal = R$ 8.833,50.","80":"N\u00c3O H\u00c1 PUBLICA\u00c7\u00c3O NESTE PER\u00cdODO","81":"N\u00c3O H\u00c1 PUBLICA\u00c7\u00c3O NESTE PER\u00cdODO","82":"Altera\u00e7\u00e3o para a marca PILOT dos pinc\u00e9is para uso em quadros imantados brancos, dos itens 60, 61 e 62, constantes da subcl\u00e1usula 2.1 do contrato.","83":"Altera\u00e7\u00e3o da cl\u00e1usula segunda da ARP, para substitui\u00e7\u00e3o da Marca JUC\u00c1 pela Marca \u00c1GUA VIDA.","84":"Altera\u00e7\u00e3o da cl\u00e1usula segunda da ARP, em seu item 2.1 e 2.1.1, para excluir coluna de valor global de 24 meses e retificar o valor global estimado da Ata, que tem vig\u00eancia de 12 meses.","85":"Altera\u00e7\u00e3o da cl\u00e1usula segunda da ARP em seu item 2.1 e 2.1.1. para excluir coluna de valor global para 24 meses e retifica\u00e7\u00e3o do valor global estimado da ata, que tem vig\u00eancia de 12 meses.","86":"Altera\u00e7\u00e3o da cl\u00e1usula segunda da ARP em seu item 2.1.1 e inclus\u00e3o do item 2.1.2 para consignar os valores para execu\u00e7\u00e3o contratual da ARP, conforme segue: \"2.1.1. O valor global estimado desta ata para 12 meses de execu\u00e7\u00e3o contratual \u00e9 de R$ 1.621.698,00; 2.1.2. O valor global estimado desta ata para 24 meses de execu\u00e7\u00e3o contratual \u00e9 de R$ 3.243.396,00\".","87":"Altera\u00e7\u00e3o da reda\u00e7\u00e3o do item 2.1.1 e inclus\u00e3o do item 2.1.2 para consignar os valores para execu\u00e7\u00e3o contratual da ARP, conforme segue: para 12 meses-R$ 3.292.140,00, para 24 meses-R$ 6.584.280,00.","88":"Altera\u00e7\u00e3o da reda\u00e7\u00e3o do item 2.1.1 e inclus\u00e3o do item 2.1.2 para consignar os valores para execu\u00e7\u00e3o contratual da ARP, conforme segue: para 12 meses-R$ 1.200.000,00, para 24 meses-R$ 2.400.000,00.","89":"Altera\u00e7\u00e3o da reda\u00e7\u00e3o do item 2.1.1 e inclus\u00e3o do item 2.1.2 para consignar os valores, conforme segue: para 12 meses-R$ 476.760,00, para 24 meses-R$ 953.520,00.","90":"N\u00c3O H\u00c1 PUBLICA\u00c7\u00c3O NESTE PER\u00cdODO","91":"Corre\u00e7\u00e3o do valor constante no item 2.1 da Cl\u00e1usula 2\u00aa, em virtude de equ\u00edvoco no registro do valor total mensal: \"2.1. O valor total mensal da presente ata \u00e9 de R$ 77.422,20 e o valor anual \u00e9 de R$ 929.066,40, conforme o disposto na proposta contratada.\"","92":"N\u00c3O H\u00c1 PUBLICA\u00c7\u00c3O NESTE PER\u00cdODO","93":"Fica alterada a marca e o modelo do item 10, constante da subcl\u00e1usula 2.1., por interesse p\u00fablico, em virtude da marca anterior ter tido sua produ\u00e7\u00e3o interrompida.                                                                - Condicionador de ar tipo Split System de 36.000 BTU\/h, 220V\/1f\/60Hz, tipo Piso\/Teto, tecnologia convencional (n\u00e3o inverter), ciclo frio ou quente\/frio, cor branca, unidade evaporadora Piso\/Teto e unidade condensadora com serpentina de cobre e com ventila\u00e7\u00e3o de fluxo vertical (um condensador para um evaporador), compressor rotativo, classifica\u00e7\u00e3o energ\u00e9tica com certifica\u00e7\u00e3o Inmetro \u2013 Selo Procel \u201cB\u201d, controle remoto sem fio. Marca\/Modelo: KOMECO \/ KOP36FC 1LX (R-410A).","94":"Altera\u00e7\u00e3o do item 03 constante da subcl\u00e1usula 2.1. (para Marca: AGRATTO - Modelo ACS12FR4), por interesse p\u00fablico, em raz\u00e3o da demora da marca CONFEE em rela\u00e7\u00e3o a sua fabrica\u00e7\u00e3o e entrega.","95":"Retifica\u00e7\u00e3o da cl\u00e1usula segunda da ARP correlata, que trata dos pre\u00e7os registrados, para alterar o valor global do intem 01 e o valor unit\u00e1rio do item 03, quais sejam: R$ 25.460,00 e R$ 187,00, respectivamente.","96":"Substitui\u00e7\u00e3o da titularidade das obriga\u00e7\u00f5es contratuais relativas \u00e0 Ata de Registro de Pre\u00e7os n\u00ba 069\/2018-MP\/PA, da empresa R. da Costa Teixeira Servi\u00e7os - EPP para a Empresa Mobiliza Rent a Car Ltda, devido a ocorr\u00eancia de cis\u00e3o societ\u00e1ria.","97":"Substitui\u00e7\u00e3o da titularidade das obriga\u00e7\u00f5es contratuais relativas \u00e0 Ata de Registro de Pre\u00e7os n\u00ba 069\/2018-MP\/PA, da empresa R. da Costa Teixeira Servi\u00e7os - EPP para a Empresa Mobiliza Rent a Car Ltda, devido a ocorr\u00eancia de cis\u00e3o societ\u00e1ria.","98":"Substitui\u00e7\u00e3o da titularidade das obriga\u00e7\u00f5es contratuais relativas \u00e0 Ata de Registro de Pre\u00e7os n\u00ba 072\/2018-MP\/PA, da Empresa R. da Costa Teixeira Servi\u00e7os Eireli-EPP para Empresa Mobiliza Rent a Car Ltda, devido a ocorr\u00eancia de cis\u00e3o societ\u00e1ria.","99":"N\u00c3O H\u00c1 PUBLICA\u00c7\u00c3O NESTE PER\u00cdODO","100":"N\u00c3O H\u00c1 PUBLICA\u00c7\u00c3O NESTE PER\u00cdODO","101":"N\u00c3O H\u00c1 PUBLICA\u00c7\u00c3O NESTE PER\u00cdODO","102":"Altera\u00e7\u00e3o do material ofertado na ARP.","103":"Altera\u00e7\u00e3o da cl\u00e1usula 2\u00aa, item 2.1, considerando o equ\u00edvoco no registro do valor unit\u00e1rio no item 2.1 (tabela) e para coadunar com o valor registrado na proposta comercial.","104":"N\u00c3O H\u00c1 PUBLICA\u00c7\u00c3O NESTE PER\u00cdODO","105":"Corre\u00e7\u00e3o do valor unit\u00e1rio do item 19 (tabela), da Cl\u00e1usula SEGUNDA da ARP 062\/2019.","106":"N\u00c3O H\u00c1 PUBLICA\u00c7\u00c3O NESTE PER\u00cdODO","107":"N\u00c3O H\u00c1 PUBLICA\u00c7\u00c3O NESTE PER\u00cdODO","108":"N\u00c3O H\u00c1 PUBLICA\u00c7\u00c3O NESTE PER\u00cdODO","109":"N\u00c3O H\u00c1 PUBLICA\u00c7\u00c3O NESTE PER\u00cdODO","110":"Altera\u00e7\u00e3o do modelo do item 05, constante da subcl\u00e1usula 2.1, por interesse p\u00fablico.","111":"N\u00c3O H\u00c1 PUBLICA\u00c7\u00c3O NESTE PER\u00cdODO","112":"N\u00c3O H\u00c1 PUBLICA\u00c7\u00c3O NESTE PER\u00cdODO","113":"N\u00c3O H\u00c1 PUBLICA\u00c7\u00c3O NESTE PER\u00cdODO","114":"N\u00c3O H\u00c1 PUBLICA\u00c7\u00c3O NESTE PER\u00cdODO"},"Data da Publica\u00e7\u00e3o (d)":{"0":"08\/03\/2012","1":"12\/03\/2012","2":"12\/03\/2012","3":"12\/03\/2012","4":"11\/04\/2012","5":"07\/05\/2012","6":"11\/06\/2012","7":"11\/07\/2012","8":"02\/08\/2012","9":"31\/08\/2012","10":"06\/09\/2012","11":"22\/11\/2012","12":"19\/12\/2012","13":"19\/12\/2012","14":"08\/02\/2013","15":"30\/07\/2013","16":"28\/02\/2014","17":"08\/04\/2014","18":"28\/05\/2014","19":"19\/12\/2014","20":"20\/01\/2015","21":"05\/02\/2015","22":"0","23":"0","24":"0","25":"0","26":"0","27":"31\/08\/2015","28":"0","29":"22\/10\/2015","30":"03\/11\/2015","31":"09\/12\/2015","32":"09\/12\/2015","33":"21\/12\/2015","34":"0","35":"0","36":"16\/03\/2016","37":"0","38":"18\/05\/2016","39":"15\/06\/2016","40":"0","41":"18\/08\/2016","42":"23\/08\/2016","43":"13\/09\/2016","44":"0","45":"03\/11\/2016","46":"0","47":"30\/01\/2017","48":"21\/02\/2017","49":"31\/03\/2017","50":"31\/03\/2017","51":"31\/03\/2017","52":"0","53":"0","54":"0","55":"05\/07\/2017","56":"05\/07\/2017","57":"05\/07\/2017","58":"05\/07\/2017","59":"13\/07\/2017","60":"13\/07\/2017","61":"13\/07\/2017","62":"13\/07\/2017","63":"13\/07\/2017","64":"13\/07\/2017","65":"13\/07\/2017","66":"13\/07\/2017","67":"17\/07\/2017","68":"26\/07\/2017","69":"0","70":"01\/09\/2017","71":"04\/09\/2017","72":"27\/09\/2017","73":"13\/10\/2017","74":"17\/10\/2017","75":"0","76":"0","77":"0","78":"0","79":"09\/03\/2018","80":"0","81":"0","82":"15\/06\/2018","83":"05\/07\/2018","84":"16\/07\/2018","85":"02\/08\/2018","86":"14\/08\/2018","87":"22\/08\/2018","88":"22\/08\/2018","89":"28\/08\/2018","90":"0","91":"10\/10\/2018","92":"0","93":"12\/07\/2018","94":"09\/01\/2019","95":"14\/02\/2019","96":"15\/03\/2019","97":"15\/03\/2019","98":"15\/03\/2019","99":"0","100":"0","101":"0","102":"23\/07\/2019","103":"05\/07\/2019","104":"0","105":"16\/09\/2019","106":"0","107":"0","108":"0","109":"0","110":"13\/02\/2020","111":"0","112":"0","113":"0","114":"0"},"M\u00eas":{"0":3,"1":3,"2":3,"3":3,"4":4,"5":5,"6":6,"7":7,"8":8,"9":8,"10":9,"11":11,"12":12,"13":12,"14":2,"15":7,"16":2,"17":4,"18":5,"19":12,"20":1,"21":2,"22":3,"23":4,"24":5,"25":6,"26":7,"27":8,"28":9,"29":10,"30":11,"31":12,"32":12,"33":12,"34":1,"35":2,"36":3,"37":4,"38":5,"39":6,"40":7,"41":8,"42":8,"43":9,"44":10,"45":11,"46":12,"47":1,"48":2,"49":3,"50":3,"51":3,"52":4,"53":5,"54":6,"55":7,"56":7,"57":7,"58":7,"59":7,"60":7,"61":7,"62":7,"63":7,"64":7,"65":7,"66":7,"67":7,"68":7,"69":8,"70":9,"71":9,"72":9,"73":10,"74":10,"75":11,"76":12,"77":1,"78":2,"79":3,"80":4,"81":5,"82":6,"83":7,"84":7,"85":8,"86":8,"87":8,"88":8,"89":8,"90":9,"91":10,"92":11,"93":12,"94":1,"95":2,"96":3,"97":3,"98":3,"99":4,"100":5,"101":6,"102":7,"103":7,"104":8,"105":9,"106":10,"107":11,"108":12,"109":1,"110":2,"111":3,"112":4,"113":5,"114":6},"Ano":{"0":2012,"1":2012,"2":2012,"3":2012,"4":2012,"5":2012,"6":2012,"7":2012,"8":2012,"9":2012,"10":2012,"11":2012,"12":2012,"13":2012,"14":2013,"15":2013,"16":2014,"17":2014,"18":2014,"19":2014,"20":2015,"21":2015,"22":2015,"23":2015,"24":2015,"25":2015,"26":2015,"27":2015,"28":2015,"29":2015,"30":2015,"31":2015,"32":2015,"33":2015,"34":2016,"35":2016,"36":2016,"37":2016,"38":2016,"39":2016,"40":2016,"41":2016,"42":2016,"43":2016,"44":2016,"45":2016,"46":2016,"47":2017,"48":2017,"49":2017,"50":2017,"51":2017,"52":2017,"53":2017,"54":2017,"55":2017,"56":2017,"57":2017,"58":2017,"59":2017,"60":2017,"61":2017,"62":2017,"63":2017,"64":2017,"65":2017,"66":2017,"67":2017,"68":2017,"69":2017,"70":2017,"71":2017,"72":2017,"73":2017,"74":2017,"75":2017,"76":2017,"77":2018,"78":2018,"79":2018,"80":2018,"81":2018,"82":2018,"83":2018,"84":2018,"85":2018,"86":2018,"87":2018,"88":2018,"89":2018,"90":2018,"91":2018,"92":2018,"93":2018,"94":2019,"95":2019,"96":2019,"97":2019,"98":2019,"99":2019,"100":2019,"101":2019,"102":2019,"103":2019,"104":2019,"105":2019,"106":2019,"107":2019,"108":2019,"109":2020,"110":2020,"111":2020,"112":2020,"113":2020,"114":2020}}